{
  "id": "00000000-0000-0000-0000-000000000000",
  "prevId": "",
  "version": "7",
  "dialect": "postgresql",
  "tables": {
    "public.Network": {
      "name": "Network",
      "schema": "",
      "columns": {
        "slug": {
          "name": "slug",
          "type": "text",
          "primaryKey": false,
          "notNull": true
        },
        "tmdbId": {
          "name": "tmdbId",
          "type": "integer",
          "primaryKey": false,
          "notNull": true
        },
        "logoPath": {
          "name": "logoPath",
          "type": "text",
          "primaryKey": false,
          "notNull": true
        },
        "name": {
          "name": "name",
          "type": "text",
          "primaryKey": false,
          "notNull": true
        },
        "country": {
          "name": "country",
          "type": "text",
          "primaryKey": false,
          "notNull": true
        },
        "createdAt": {
          "name": "createdAt",
          "type": "timestamp(3)",
          "primaryKey": false,
          "notNull": true,
          "default": "CURRENT_TIMESTAMP"
        },
        "updatedAt": {
          "name": "updatedAt",
          "type": "timestamp(3)",
          "primaryKey": false,
          "notNull": true,
          "default": "CURRENT_TIMESTAMP"
        },
        "id": {
          "name": "id",
          "type": "serial",
          "primaryKey": true,
          "notNull": true
        }
      },
      "indexes": {
        "Network_slug_key": {
          "name": "Network_slug_key",
          "columns": [
            {
              "expression": "slug",
              "asc": true,
              "nulls": "last",
              "opclass": "text_ops",
              "isExpression": false
            }
          ],
          "isUnique": true,
          "concurrently": false,
          "method": "btree",
          "with": {}
        },
        "Network_tmdbId_key": {
          "name": "Network_tmdbId_key",
          "columns": [
            {
              "expression": "tmdbId",
              "asc": true,
              "nulls": "last",
              "opclass": "int4_ops",
              "isExpression": false
            }
          ],
          "isUnique": true,
          "concurrently": false,
          "method": "btree",
          "with": {}
        }
      },
      "foreignKeys": {},
      "compositePrimaryKeys": {},
      "uniqueConstraints": {},
      "checkConstraints": {},
      "policies": {},
      "isRLSEnabled": false
    },
    "public.Genre": {
      "name": "Genre",
      "schema": "",
      "columns": {
        "tmdbId": {
          "name": "tmdbId",
          "type": "integer",
          "primaryKey": false,
          "notNull": true
        },
        "name": {
          "name": "name",
          "type": "text",
          "primaryKey": false,
          "notNull": true
        },
        "slug": {
          "name": "slug",
          "type": "text",
          "primaryKey": false,
          "notNull": true
        },
        "createdAt": {
          "name": "createdAt",
          "type": "timestamp(3)",
          "primaryKey": false,
          "notNull": true,
          "default": "CURRENT_TIMESTAMP"
        },
        "updatedAt": {
          "name": "updatedAt",
          "type": "timestamp(3)",
          "primaryKey": false,
          "notNull": true,
          "default": "CURRENT_TIMESTAMP"
        },
        "id": {
          "name": "id",
          "type": "serial",
          "primaryKey": true,
          "notNull": true
        }
      },
      "indexes": {
        "Genre_name_key": {
          "name": "Genre_name_key",
          "columns": [
            {
              "expression": "name",
              "asc": true,
              "nulls": "last",
              "opclass": "text_ops",
              "isExpression": false
            }
          ],
          "isUnique": true,
          "concurrently": false,
          "method": "btree",
          "with": {}
        },
        "Genre_slug_key": {
          "name": "Genre_slug_key",
          "columns": [
            {
              "expression": "slug",
              "asc": true,
              "nulls": "last",
              "opclass": "text_ops",
              "isExpression": false
            }
          ],
          "isUnique": true,
          "concurrently": false,
          "method": "btree",
          "with": {}
        },
        "Genre_tmdbId_key": {
          "name": "Genre_tmdbId_key",
          "columns": [
            {
              "expression": "tmdbId",
              "asc": true,
              "nulls": "last",
              "opclass": "int4_ops",
              "isExpression": false
            }
          ],
          "isUnique": true,
          "concurrently": false,
          "method": "btree",
          "with": {}
        }
      },
      "foreignKeys": {},
      "compositePrimaryKeys": {},
      "uniqueConstraints": {},
      "checkConstraints": {},
      "policies": {},
      "isRLSEnabled": false
    },
    "public.Language": {
      "name": "Language",
      "schema": "",
      "columns": {
        "name": {
          "name": "name",
          "type": "text",
          "primaryKey": false,
          "notNull": true
        },
        "createdAt": {
          "name": "createdAt",
          "type": "timestamp(3)",
          "primaryKey": false,
          "notNull": true,
          "default": "CURRENT_TIMESTAMP"
        },
        "updatedAt": {
          "name": "updatedAt",
          "type": "timestamp(3)",
          "primaryKey": false,
          "notNull": true,
          "default": "CURRENT_TIMESTAMP"
        },
        "id": {
          "name": "id",
          "type": "serial",
          "primaryKey": true,
          "notNull": true
        }
      },
      "indexes": {},
      "foreignKeys": {},
      "compositePrimaryKeys": {},
      "uniqueConstraints": {},
      "checkConstraints": {},
      "policies": {},
      "isRLSEnabled": false
    },
    "public.Media": {
      "name": "Media",
      "schema": "",
      "columns": {
        "tmdbId": {
          "name": "tmdbId",
          "type": "integer",
          "primaryKey": false,
          "notNull": true
        },
        "season": {
          "name": "season",
          "type": "integer",
          "primaryKey": false,
          "notNull": true
        },
        "imdbId": {
          "name": "imdbId",
          "type": "text",
          "primaryKey": false,
          "notNull": false
        },
        "backdropImages": {
          "name": "backdropImages",
          "type": "text[]",
          "primaryKey": false,
          "notNull": false
        },
        "posterImages": {
          "name": "posterImages",
          "type": "text[]",
          "primaryKey": false,
          "notNull": false
        },
        "videos": {
          "name": "videos",
          "type": "text[]",
          "primaryKey": false,
          "notNull": false
        },
        "title": {
          "name": "title",
          "type": "text",
          "primaryKey": false,
          "notNull": true
        },
        "originalTitle": {
          "name": "originalTitle",
          "type": "text",
          "primaryKey": false,
          "notNull": true
        },
        "alternativeTitles": {
          "name": "alternativeTitles",
          "type": "text[]",
          "primaryKey": false,
          "notNull": false
        },
        "overview": {
          "name": "overview",
          "type": "text",
          "primaryKey": false,
          "notNull": true
        },
        "releaseDate": {
          "name": "releaseDate",
          "type": "text",
          "primaryKey": false,
          "notNull": true
        },
        "posterPath": {
          "name": "posterPath",
          "type": "text",
          "primaryKey": false,
          "notNull": false
        },
        "backdropPath": {
          "name": "backdropPath",
          "type": "text",
          "primaryKey": false,
          "notNull": false
        },
        "status": {
          "name": "status",
          "type": "text",
          "primaryKey": false,
          "notNull": false
        },
        "popularity": {
          "name": "popularity",
          "type": "double precision",
          "primaryKey": false,
          "notNull": true,
          "default": 0
        },
        "rating": {
          "name": "rating",
          "type": "double precision",
          "primaryKey": false,
          "notNull": true,
          "default": 0
        },
        "adult": {
          "name": "adult",
          "type": "boolean",
          "primaryKey": false,
          "notNull": true,
          "default": false
        },
        "tagline": {
          "name": "tagline",
          "type": "text",
          "primaryKey": false,
          "notNull": false
        },
        "mediaType": {
          "name": "mediaType",
          "type": "MediaType",
          "typeSchema": "public",
          "primaryKey": false,
          "notNull": true
        },
        "createdAt": {
          "name": "createdAt",
          "type": "timestamp(3)",
          "primaryKey": false,
          "notNull": true,
          "default": "CURRENT_TIMESTAMP"
        },
        "updatedAt": {
          "name": "updatedAt",
          "type": "timestamp(3)",
          "primaryKey": false,
          "notNull": true,
          "default": "CURRENT_TIMESTAMP"
        },
        "id": {
          "name": "id",
          "type": "serial",
          "primaryKey": true,
          "notNull": true
        }
      },
      "indexes": {
        "Media_mediaType_tmdbId_season_key": {
          "name": "Media_mediaType_tmdbId_season_key",
          "columns": [
            {
              "expression": "mediaType",
              "asc": true,
              "nulls": "last",
              "opclass": "int4_ops",
              "isExpression": false
            },
            {
              "expression": "tmdbId",
              "asc": true,
              "nulls": "last",
              "opclass": "int4_ops",
              "isExpression": false
            },
            {
              "expression": "season",
              "asc": true,
              "nulls": "last",
              "opclass": "int4_ops",
              "isExpression": false
            }
          ],
          "isUnique": true,
          "concurrently": false,
          "method": "btree",
          "with": {}
        }
      },
      "foreignKeys": {},
      "compositePrimaryKeys": {},
      "uniqueConstraints": {},
      "checkConstraints": {},
      "policies": {},
      "isRLSEnabled": false
    },
    "public.Player": {
      "name": "Player",
      "schema": "",
      "columns": {
        "url": {
          "name": "url",
          "type": "text",
          "primaryKey": false,
          "notNull": true
        },
        "languageName": {
          "name": "languageName",
          "type": "text",
          "primaryKey": false,
          "notNull": true
        },
        "videoHostName": {
          "name": "videoHostName",
          "type": "text",
          "primaryKey": false,
          "notNull": true
        },
        "createdAt": {
          "name": "createdAt",
          "type": "timestamp(3)",
          "primaryKey": false,
          "notNull": true,
          "default": "CURRENT_TIMESTAMP"
        },
        "updatedAt": {
          "name": "updatedAt",
          "type": "timestamp(3)",
          "primaryKey": false,
          "notNull": true,
          "default": "CURRENT_TIMESTAMP"
        },
        "id": {
          "name": "id",
          "type": "serial",
          "primaryKey": true,
          "notNull": true
        },
        "episodeId": {
          "name": "episodeId",
          "type": "integer",
          "primaryKey": false,
          "notNull": true
        }
      },
      "indexes": {
        "Player_url_key": {
          "name": "Player_url_key",
          "columns": [
            {
              "expression": "url",
              "asc": true,
              "nulls": "last",
              "opclass": "text_ops",
              "isExpression": false
            }
          ],
          "isUnique": true,
          "concurrently": false,
          "method": "btree",
          "with": {}
        }
      },
      "foreignKeys": {
        "Player_languageName_fkey": {
          "name": "Player_languageName_fkey",
          "tableFrom": "Player",
          "tableTo": "Language",
          "schemaTo": "public",
          "columnsFrom": [
            "languageName"
          ],
          "columnsTo": [
            "name"
          ],
          "onDelete": "cascade",
          "onUpdate": "cascade"
        },
        "Player_videoHostName_fkey": {
          "name": "Player_videoHostName_fkey",
          "tableFrom": "Player",
          "tableTo": "VideoHost",
          "schemaTo": "public",
          "columnsFrom": [
            "videoHostName"
          ],
          "columnsTo": [
            "name"
          ],
          "onDelete": "cascade",
          "onUpdate": "cascade"
        },
        "Player_episodeId_fkey": {
          "name": "Player_episodeId_fkey",
          "tableFrom": "Player",
          "tableTo": "Episode",
          "schemaTo": "public",
          "columnsFrom": [
            "episodeId"
          ],
          "columnsTo": [
            "id"
          ],
          "onDelete": "cascade",
          "onUpdate": "cascade"
        }
      },
      "compositePrimaryKeys": {},
      "uniqueConstraints": {},
      "checkConstraints": {},
      "policies": {},
      "isRLSEnabled": false
    },
    "public.VideoHost": {
      "name": "VideoHost",
      "schema": "",
      "columns": {
        "name": {
          "name": "name",
          "type": "text",
          "primaryKey": false,
          "notNull": true
        },
        "slug": {
          "name": "slug",
          "type": "text",
          "primaryKey": false,
          "notNull": true
        },
        "priority": {
          "name": "priority",
          "type": "integer",
          "primaryKey": false,
          "notNull": true,
          "default": 10
        },
        "createdAt": {
          "name": "createdAt",
          "type": "timestamp(3)",
          "primaryKey": false,
          "notNull": true,
          "default": "CURRENT_TIMESTAMP"
        },
        "updatedAt": {
          "name": "updatedAt",
          "type": "timestamp(3)",
          "primaryKey": false,
          "notNull": true,
          "default": "CURRENT_TIMESTAMP"
        },
        "id": {
          "name": "id",
          "type": "serial",
          "primaryKey": true,
          "notNull": true
        }
      },
      "indexes": {},
      "foreignKeys": {},
      "compositePrimaryKeys": {},
      "uniqueConstraints": {},
      "checkConstraints": {},
      "policies": {},
      "isRLSEnabled": false
    },
    "public.WatchProvider": {
      "name": "WatchProvider",
      "schema": "",
      "columns": {
        "slug": {
          "name": "slug",
          "type": "text",
          "primaryKey": false,
          "notNull": true
        },
        "tmdbId": {
          "name": "tmdbId",
          "type": "integer",
          "primaryKey": false,
          "notNull": true
        },
        "name": {
          "name": "name",
          "type": "text",
          "primaryKey": false,
          "notNull": true
        },
        "logoPath": {
          "name": "logoPath",
          "type": "text",
          "primaryKey": false,
          "notNull": true
        },
        "priority": {
          "name": "priority",
          "type": "integer",
          "primaryKey": false,
          "notNull": true,
          "default": 20
        },
        "createdAt": {
          "name": "createdAt",
          "type": "timestamp(3)",
          "primaryKey": false,
          "notNull": true,
          "default": "CURRENT_TIMESTAMP"
        },
        "updatedAt": {
          "name": "updatedAt",
          "type": "timestamp(3)",
          "primaryKey": false,
          "notNull": true,
          "default": "CURRENT_TIMESTAMP"
        },
        "id": {
          "name": "id",
          "type": "serial",
          "primaryKey": true,
          "notNull": true
        }
      },
      "indexes": {
        "WatchProvider_slug_key": {
          "name": "WatchProvider_slug_key",
          "columns": [
            {
              "expression": "slug",
              "asc": true,
              "nulls": "last",
              "opclass": "text_ops",
              "isExpression": false
            }
          ],
          "isUnique": true,
          "concurrently": false,
          "method": "btree",
          "with": {}
        },
        "WatchProvider_tmdbId_key": {
          "name": "WatchProvider_tmdbId_key",
          "columns": [
            {
              "expression": "tmdbId",
              "asc": true,
              "nulls": "last",
              "opclass": "int4_ops",
              "isExpression": false
            }
          ],
          "isUnique": true,
          "concurrently": false,
          "method": "btree",
          "with": {}
        }
      },
      "foreignKeys": {},
      "compositePrimaryKeys": {},
      "uniqueConstraints": {},
      "checkConstraints": {},
      "policies": {},
      "isRLSEnabled": false
    },
    "public.Episode": {
      "name": "Episode",
      "schema": "",
      "columns": {
        "season": {
          "name": "season",
          "type": "integer",
          "primaryKey": false,
          "notNull": true
        },
        "number": {
          "name": "number",
          "type": "integer",
          "primaryKey": false,
          "notNull": true
        },
        "runtime": {
          "name": "runtime",
          "type": "integer",
          "primaryKey": false,
          "notNull": true,
          "default": 0
        },
        "rating": {
          "name": "rating",
          "type": "double precision",
          "primaryKey": false,
          "notNull": true,
          "default": 0
        },
        "title": {
          "name": "title",
          "type": "text",
          "primaryKey": false,
          "notNull": false
        },
        "releaseDate": {
          "name": "releaseDate",
          "type": "text",
          "primaryKey": false,
          "notNull": false
        },
        "description": {
          "name": "description",
          "type": "text",
          "primaryKey": false,
          "notNull": false
        },
        "stillPath": {
          "name": "stillPath",
          "type": "text",
          "primaryKey": false,
          "notNull": false
        },
        "createdAt": {
          "name": "createdAt",
          "type": "timestamp(3)",
          "primaryKey": false,
          "notNull": true,
          "default": "CURRENT_TIMESTAMP"
        },
        "updatedAt": {
          "name": "updatedAt",
          "type": "timestamp(3)",
          "primaryKey": false,
          "notNull": true,
          "default": "CURRENT_TIMESTAMP"
        },
        "id": {
          "name": "id",
          "type": "serial",
          "primaryKey": true,
          "notNull": true
        },
        "mediaId": {
          "name": "mediaId",
          "type": "integer",
          "primaryKey": false,
          "notNull": true
        }
      },
      "indexes": {
        "Episode_mediaId_season_number_key": {
          "name": "Episode_mediaId_season_number_key",
          "columns": [
            {
              "expression": "mediaId",
              "asc": true,
              "nulls": "last",
              "opclass": "int4_ops",
              "isExpression": false
            },
            {
              "expression": "season",
              "asc": true,
              "nulls": "last",
              "opclass": "int4_ops",
              "isExpression": false
            },
            {
              "expression": "number",
              "asc": true,
              "nulls": "last",
              "opclass": "int4_ops",
              "isExpression": false
            }
          ],
          "isUnique": true,
          "concurrently": false,
          "method": "btree",
          "with": {}
        }
      },
      "foreignKeys": {
        "Episode_mediaId_fkey": {
          "name": "Episode_mediaId_fkey",
          "tableFrom": "Episode",
          "tableTo": "Media",
          "schemaTo": "public",
          "columnsFrom": [
            "mediaId"
          ],
          "columnsTo": [
            "id"
          ],
          "onDelete": "cascade",
          "onUpdate": "cascade"
        }
      },
      "compositePrimaryKeys": {},
      "uniqueConstraints": {},
      "checkConstraints": {},
      "policies": {},
      "isRLSEnabled": false
    },
    "public._MediaToNetwork": {
      "name": "_MediaToNetwork",
      "schema": "",
      "columns": {
        "A": {
          "name": "A",
          "type": "integer",
          "primaryKey": false,
          "notNull": true
        },
        "B": {
          "name": "B",
          "type": "integer",
          "primaryKey": false,
          "notNull": true
        }
      },
      "indexes": {
        "_MediaToNetwork_B_index": {
          "name": "_MediaToNetwork_B_index",
          "columns": [
            {
              "expression": "B",
              "asc": true,
              "nulls": "last",
              "opclass": "int4_ops",
              "isExpression": false
            }
          ],
          "isUnique": false,
          "concurrently": false,
          "method": "btree",
          "with": {}
        }
      },
      "foreignKeys": {
        "_MediaToNetwork_A_fkey": {
          "name": "_MediaToNetwork_A_fkey",
          "tableFrom": "_MediaToNetwork",
          "tableTo": "Media",
          "schemaTo": "public",
          "columnsFrom": [
            "A"
          ],
          "columnsTo": [
            "id"
          ],
          "onDelete": "cascade",
          "onUpdate": "cascade"
        },
        "_MediaToNetwork_B_fkey": {
          "name": "_MediaToNetwork_B_fkey",
          "tableFrom": "_MediaToNetwork",
          "tableTo": "Network",
          "schemaTo": "public",
          "columnsFrom": [
            "B"
          ],
          "columnsTo": [
            "id"
          ],
          "onDelete": "cascade",
          "onUpdate": "cascade"
        }
      },
      "compositePrimaryKeys": {
        "_MediaToNetwork_AB_pkey": {
          "name": "_MediaToNetwork_AB_pkey",
          "columns": [
            "A",
            "B"
          ]
        }
      },
      "uniqueConstraints": {},
      "checkConstraints": {},
      "policies": {},
      "isRLSEnabled": false
    },
    "public._MediaToWatchProvider": {
      "name": "_MediaToWatchProvider",
      "schema": "",
      "columns": {
        "A": {
          "name": "A",
          "type": "integer",
          "primaryKey": false,
          "notNull": true
        },
        "B": {
          "name": "B",
          "type": "integer",
          "primaryKey": false,
          "notNull": true
        }
      },
      "indexes": {
        "_MediaToWatchProvider_B_index": {
          "name": "_MediaToWatchProvider_B_index",
          "columns": [
            {
              "expression": "B",
              "asc": true,
              "nulls": "last",
              "opclass": "int4_ops",
              "isExpression": false
            }
          ],
          "isUnique": false,
          "concurrently": false,
          "method": "btree",
          "with": {}
        }
      },
      "foreignKeys": {
        "_MediaToWatchProvider_A_fkey": {
          "name": "_MediaToWatchProvider_A_fkey",
          "tableFrom": "_MediaToWatchProvider",
          "tableTo": "Media",
          "schemaTo": "public",
          "columnsFrom": [
            "A"
          ],
          "columnsTo": [
            "id"
          ],
          "onDelete": "cascade",
          "onUpdate": "cascade"
        },
        "_MediaToWatchProvider_B_fkey": {
          "name": "_MediaToWatchProvider_B_fkey",
          "tableFrom": "_MediaToWatchProvider",
          "tableTo": "WatchProvider",
          "schemaTo": "public",
          "columnsFrom": [
            "B"
          ],
          "columnsTo": [
            "id"
          ],
          "onDelete": "cascade",
          "onUpdate": "cascade"
        }
      },
      "compositePrimaryKeys": {
        "_MediaToWatchProvider_AB_pkey": {
          "name": "_MediaToWatchProvider_AB_pkey",
          "columns": [
            "A",
            "B"
          ]
        }
      },
      "uniqueConstraints": {},
      "checkConstraints": {},
      "policies": {},
      "isRLSEnabled": false
    },
    "public._GenreToMedia": {
      "name": "_GenreToMedia",
      "schema": "",
      "columns": {
        "A": {
          "name": "A",
          "type": "integer",
          "primaryKey": false,
          "notNull": true
        },
        "B": {
          "name": "B",
          "type": "integer",
          "primaryKey": false,
          "notNull": true
        }
      },
      "indexes": {
        "_GenreToMedia_B_index": {
          "name": "_GenreToMedia_B_index",
          "columns": [
            {
              "expression": "B",
              "asc": true,
              "nulls": "last",
              "opclass": "int4_ops",
              "isExpression": false
            }
          ],
          "isUnique": false,
          "concurrently": false,
          "method": "btree",
          "with": {}
        }
      },
      "foreignKeys": {
        "_GenreToMedia_A_fkey": {
          "name": "_GenreToMedia_A_fkey",
          "tableFrom": "_GenreToMedia",
          "tableTo": "Genre",
          "schemaTo": "public",
          "columnsFrom": [
            "A"
          ],
          "columnsTo": [
            "id"
          ],
          "onDelete": "cascade",
          "onUpdate": "cascade"
        },
        "_GenreToMedia_B_fkey": {
          "name": "_GenreToMedia_B_fkey",
          "tableFrom": "_GenreToMedia",
          "tableTo": "Media",
          "schemaTo": "public",
          "columnsFrom": [
            "B"
          ],
          "columnsTo": [
            "id"
          ],
          "onDelete": "cascade",
          "onUpdate": "cascade"
        }
      },
      "compositePrimaryKeys": {
        "_GenreToMedia_AB_pkey": {
          "name": "_GenreToMedia_AB_pkey",
          "columns": [
            "A",
            "B"
          ]
        }
      },
      "uniqueConstraints": {},
      "checkConstraints": {},
      "policies": {},
      "isRLSEnabled": false
    }
  },
  "enums": {
    "public.MediaType": {
      "name": "MediaType",
      "values": [
        "series",
        "movies"
      ],
      "schema": "public"
    }
  },
  "schemas": {},
  "sequences": {},
  "roles": {},
  "policies": {},
  "views": {},
  "_meta": {
    "schemas": {},
    "tables": {},
    "columns": {}
  },
  "internal": {
    "tables": {
      "Media": {
        "columns": {
          "backdropImages": {
            "isArray": true,
            "dimensions": 1,
            "rawType": "text"
          },
          "posterImages": {
            "isArray": true,
            "dimensions": 1,
            "rawType": "text"
          },
          "videos": {
            "isArray": true,
            "dimensions": 1,
            "rawType": "text"
          },
          "alternativeTitles": {
            "isArray": true,
            "dimensions": 1,
            "rawType": "text"
          }
        }
      }
    }
  }
}